MANIFEST.in
README.rst
setup.cfg
setup.py
asynckafka/__init__.py
asynckafka/callbacks.c
asynckafka/callbacks.pxd
asynckafka/callbacks.pyx
asynckafka/exceptions.py
asynckafka/settings.c
asynckafka/settings.pxd
asynckafka/settings.pyx
asynckafka/utils.c
asynckafka/utils.pxd
asynckafka/utils.pyx
asynckafka.egg-info/PKG-INFO
asynckafka.egg-info/SOURCES.txt
asynckafka.egg-info/dependency_links.txt
asynckafka.egg-info/top_level.txt
asynckafka/consumer/__init__.py
asynckafka/consumer/consumer.c
asynckafka/consumer/consumer.pxd
asynckafka/consumer/consumer.pyx
asynckafka/consumer/message.c
asynckafka/consumer/message.pxd
asynckafka/consumer/message.pyx
asynckafka/consumer/rd_kafka_consumer.c
asynckafka/consumer/rd_kafka_consumer.pxd
asynckafka/consumer/rd_kafka_consumer.pyx
asynckafka/consumer/topic_partition.c
asynckafka/consumer/topic_partition.pxd
asynckafka/consumer/topic_partition.pyx
asynckafka/includes/__init__.py
asynckafka/includes/c_rd_kafka.pxd
asynckafka/producer/__init__.py
asynckafka/producer/producer.c
asynckafka/producer/producer.pxd
asynckafka/producer/producer.pyx
asynckafka/producer/rd_kafka_producer.c
asynckafka/producer/rd_kafka_producer.pxd
asynckafka/producer/rd_kafka_producer.pyx