Metadata-Version: 1.1
Name: asynckafka
Version: 0.1.3
Summary: Fast python kafka client for asyncio.
Home-page: http://github.com/jmf-mordis/asynckafka
Author: José Melero Fernández
Author-email: jmelerofernandez@gmail.com
License: MIT
Download-URL: https://github.com/jmf-mordis/asynckafka/archive/0.1.3.tar.gz
Keywords: asyncio,kafka,cython
Platform: *nix
Classifier: Development Status :: 2 - Pre-Alpha
Classifier: Programming Language :: Python :: 3 :: Only
Classifier: Programming Language :: Python :: 3.6
Classifier: Programming Language :: Python :: 3.7
Classifier: License :: OSI Approved :: MIT License
Classifier: Intended Audience :: Developers
Classifier: Framework :: AsyncIO
